monitorVW/__init__.py
monitorVW/monitorVW.py
monitorvw-2.4.0.dist-info/METADATA
monitorvw-2.4.0.dist-info/WHEEL
monitorvw-2.4.0.dist-info/licenses/LICENSE
monitorvw-2.4.0.dist-info/RECORD
