Metadata-Version: 2.3
Name: monitorVW
Version: 2.4.0
Summary: Read VW car data from We Connect and store in Influx DB
Project-URL: Homepage, https://github.com/signag/py-logging-plus
Project-URL: Issues, https://github.com/signag/py-logging-plus/issues
Author-email: signag <siegfried.nagel@t-online.de>
License-File: LICENSE
Classifier: License :: OSI Approved :: MIT License
Classifier: Operating System :: OS Independent
Classifier: Programming Language :: Python :: 3
Requires-Python: >=3.11
Requires-Dist: influxdb-client>=1.44.0
Requires-Dist: logging-plus>=1.2.0
Requires-Dist: requests>=2.32.3
Requires-Dist: weconnect>=0.60.4
